pylds
