Metadata-Version: 1.1
Name: pylds
Version: 0.0.5
Summary: Learning and inference for linear dynamical systemswith fast Cython and BLAS/LAPACK implementations
Home-page: https://github.com/mattjj/pylds
Author: Matthew James Johnson and Scott W Linderman
Author-email: mattjj@csail.mit.edu
License: MIT
Keywords: lds,linear dynamical system,kalman filter,kalman,kalman smoother,rts smoother
Platform: ALL
Classifier: Intended Audience :: Science/Research
Classifier: Programming Language :: Python
